README.md
pyproject.toml
setup.py
dynamic/__init__.py
dynamic/decorator.py
dynamic/start_server.py
dynamic/classes/__init__.py
dynamic/classes/dynamic_agent.py
dynamic/classes/logger.py
dynamic/classes/message.py
dynamic/protocols/__init__.py
dynamic/protocols/server.py
dynamic/protocols/ws.py
dynamic/request/__init__.py
dynamic/response/__init__.py
dynamic/router/__init__.py
dynamic/router/file_routes_builder.py
dynamic/router/get_file_routes.py
dynamic/router/router.py
dynamic/runners/__init__.py
dynamic/runners/callable.py
dynamic/runners/runner.py
dynamic/runners/utils.py
dynamic/runners/langchain/__init__.py
dynamic/runners/langchain/agent.py
dynamic/runners/langchain/chain.py
dynamic/runners/langchain/config.py
dynamic/static/__init__.py
dynamic_sh.egg-info/PKG-INFO
dynamic_sh.egg-info/SOURCES.txt
dynamic_sh.egg-info/dependency_links.txt
dynamic_sh.egg-info/top_level.txt